quicky/__init__.py
quicky/app.py
quicky/cli.py
quicky/di.py
quicky/exceptions.py
quicky/handlers.py
quicky/metrics.py
quicky/middleware.py
quicky/routing.py
quicky/runtime.py
quicky/serializers.py
quicky/types.py
quicky-0.1.3.dist-info/METADATA
quicky-0.1.3.dist-info/WHEEL
quicky-0.1.3.dist-info/entry_points.txt
quicky-0.1.3.dist-info/licenses/LICENSE
quicky-0.1.3.dist-info/RECORD
