Metadata-Version: 2.4
Name: quicky
Version: 0.1.3
Summary: Zero-config async web framework for rapid prototyping
Project-URL: homepage, https://github.com/Zuperrino/quicky
Project-URL: source, https://github.com/Zuperrino/quicky
Project-URL: issues, https://github.com/Zuperrino/quicky/issues
Project-URL: documentation, https://github.com/Zuperrino/quicky#readme
Project-URL: changelog, https://github.com/Zuperrino/quicky/releases
Author: Quicky Team
License: MIT
License-File: LICENSE
Keywords: asgi,async,fastapi,framework,quicky,web
Classifier: Framework :: AsyncIO
Classifier: Framework :: FastAPI
Classifier: Intended Audience :: Developers
Classifier: License :: OSI Approved :: MIT License
Classifier: Programming Language :: Python :: 3
Classifier: Programming Language :: Python :: 3.12
Classifier: Programming Language :: Python :: 3.13
Classifier: Topic :: Internet :: WWW/HTTP :: Dynamic Content
Classifier: Topic :: Software Development :: Libraries :: Application Frameworks
Requires-Python: >=3.12
Requires-Dist: httptools<0.8.0,>=0.6.1
Requires-Dist: orjson<4.0.0,>=3.10.0
Requires-Dist: pydantic<3.0.0,>=2.8.0
Requires-Dist: uvicorn<0.39.0,>=0.30.0
Provides-Extra: dev
Requires-Dist: anyio>=4.4.0; extra == 'dev'
Requires-Dist: httpx>=0.27.0; extra == 'dev'
Requires-Dist: pytest>=8.2.0; extra == 'dev'
